<database name="Kangangu">
  <exam_results>
    <hsc>None</hsc>
    <exam_result_id>1</exam_result_id>
    <chem>67.0</chem>
    <total>480.0</total>
    <eng>65.0</eng>
    <student_id>1</student_id>
    <msc>None</msc>
    <uploaded>0</uploaded>
    <bio>50.0</bio>
    <updated>0</updated>
    <his>None</his>
    <mat>78.0</mat>
    <kis>70.0</kis>
    <comp>None</comp>
    <phy>70.0</phy>
    <exam_id>3</exam_id>
    <bs>75.0</bs>
    <geo>None</geo>
    <form_pos>2</form_pos>
    <class_pos>1</class_pos>
    <points>74</points>
    <cre>55.0</cre>
    <totalled>1</totalled>
    <mean>10.6</mean>
  </exam_results>
  <exam_results>
    <hsc>None</hsc>
    <exam_result_id>2</exam_result_id>
    <chem>59.0</chem>
    <total>465.0</total>
    <eng>58.0</eng>
    <student_id>2</student_id>
    <msc>None</msc>
    <uploaded>0</uploaded>
    <bio>75.0</bio>
    <updated>0</updated>
    <his>None</his>
    <mat>96.0</mat>
    <kis>56.0</kis>
    <comp>None</comp>
    <phy>60.0</phy>
    <exam_id>3</exam_id>
    <bs>None</bs>
    <geo>61.0</geo>
    <form_pos>3</form_pos>
    <class_pos>2</class_pos>
    <points>66</points>
    <cre>56.0</cre>
    <totalled>1</totalled>
    <mean>9.4</mean>
  </exam_results>
  <exam_results>
    <hsc>67.0</hsc>
    <exam_result_id>3</exam_result_id>
    <chem>70.0</chem>
    <total>494.0</total>
    <eng>85.0</eng>
    <student_id>3</student_id>
    <msc>None</msc>
    <uploaded>0</uploaded>
    <bio>None</bio>
    <updated>0</updated>
    <his>42.0</his>
    <mat>60.0</mat>
    <kis>63.0</kis>
    <comp>None</comp>
    <phy>71.0</phy>
    <exam_id>3</exam_id>
    <bs>None</bs>
    <geo>None</geo>
    <form_pos>1</form_pos>
    <class_pos>1</class_pos>
    <points>74</points>
    <cre>78.0</cre>
    <totalled>1</totalled>
    <mean>10.6</mean>
  </exam_results>
  <exam_results>
    <hsc>None</hsc>
    <exam_result_id>4</exam_result_id>
    <chem>None</chem>
    <total>308.0</total>
    <eng>47.0</eng>
    <student_id>4</student_id>
    <msc>None</msc>
    <uploaded>0</uploaded>
    <bio>75.0</bio>
    <updated>0</updated>
    <his>None</his>
    <mat>96.0</mat>
    <kis>65.0</kis>
    <comp>None</comp>
    <phy>None</phy>
    <exam_id>3</exam_id>
    <bs>None</bs>
    <geo>25.0</geo>
    <form_pos>6</form_pos>
    <class_pos>5</class_pos>
    <points>0</points>
    <cre>None</cre>
    <totalled>1</totalled>
    <mean>0.0</mean>
  </exam_results>
  <exam_results>
    <hsc>None</hsc>
    <exam_result_id>5</exam_result_id>
    <chem>None</chem>
    <total>260.0</total>
    <eng>85.0</eng>
    <student_id>5</student_id>
    <msc>None</msc>
    <uploaded>0</uploaded>
    <bio>50.0</bio>
    <updated>0</updated>
    <his>None</his>
    <mat>20.0</mat>
    <kis>63.0</kis>
    <comp>None</comp>
    <phy>None</phy>
    <exam_id>3</exam_id>
    <bs>None</bs>
    <geo>42.0</geo>
    <form_pos>9</form_pos>
    <class_pos>6</class_pos>
    <points>0</points>
    <cre>None</cre>
    <totalled>0</totalled>
    <mean>0.0</mean>
  </exam_results>
  <exam_results>
    <hsc>None</hsc>
    <exam_result_id>6</exam_result_id>
    <chem>None</chem>
    <total>308.0</total>
    <eng>47.0</eng>
    <student_id>6</student_id>
    <msc>None</msc>
    <uploaded>0</uploaded>
    <bio>75.0</bio>
    <updated>0</updated>
    <his>None</his>
    <mat>96.0</mat>
    <kis>65.0</kis>
    <comp>None</comp>
    <phy>None</phy>
    <exam_id>3</exam_id>
    <bs>None</bs>
    <geo>25.0</geo>
    <form_pos>5</form_pos>
    <class_pos>4</class_pos>
    <points>0</points>
    <cre>None</cre>
    <totalled>0</totalled>
    <mean>0.0</mean>
  </exam_results>
  <exam_results>
    <hsc>None</hsc>
    <exam_result_id>7</exam_result_id>
    <chem>None</chem>
    <total>246.0</total>
    <eng>36.0</eng>
    <student_id>7</student_id>
    <msc>None</msc>
    <uploaded>0</uploaded>
    <bio>48.0</bio>
    <updated>0</updated>
    <his>None</his>
    <mat>45.0</mat>
    <kis>65.0</kis>
    <comp>None</comp>
    <phy>None</phy>
    <exam_id>3</exam_id>
    <bs>None</bs>
    <geo>52.0</geo>
    <form_pos>10</form_pos>
    <class_pos>7</class_pos>
    <points>0</points>
    <cre>None</cre>
    <totalled>0</totalled>
    <mean>0.0</mean>
  </exam_results>
  <exam_results>
    <hsc>None</hsc>
    <exam_result_id>8</exam_result_id>
    <chem>None</chem>
    <total>308.0</total>
    <eng>47.0</eng>
    <student_id>8</student_id>
    <msc>None</msc>
    <uploaded>0</uploaded>
    <bio>75.0</bio>
    <updated>0</updated>
    <his>None</his>
    <mat>96.0</mat>
    <kis>65.0</kis>
    <comp>None</comp>
    <phy>None</phy>
    <exam_id>3</exam_id>
    <bs>None</bs>
    <geo>25.0</geo>
    <form_pos>4</form_pos>
    <class_pos>3</class_pos>
    <points>0</points>
    <cre>None</cre>
    <totalled>0</totalled>
    <mean>0.0</mean>
  </exam_results>
  <exam_results>
    <hsc>None</hsc>
    <exam_result_id>9</exam_result_id>
    <chem>None</chem>
    <total>279.0</total>
    <eng>41.0</eng>
    <student_id>9</student_id>
    <msc>None</msc>
    <uploaded>0</uploaded>
    <bio>75.0</bio>
    <updated>0</updated>
    <his>None</his>
    <mat>69.0</mat>
    <kis>49.0</kis>
    <comp>None</comp>
    <phy>None</phy>
    <exam_id>3</exam_id>
    <bs>None</bs>
    <geo>45.0</geo>
    <form_pos>0</form_pos>
    <class_pos>0</class_pos>
    <points>0</points>
    <cre>None</cre>
    <totalled>0</totalled>
    <mean>0.0</mean>
  </exam_results>
  <exam_results>
    <hsc>None</hsc>
    <exam_result_id>10</exam_result_id>
    <chem>None</chem>
    <total>268.0</total>
    <eng>36.0</eng>
    <student_id>10</student_id>
    <msc>None</msc>
    <uploaded>0</uploaded>
    <bio>80.0</bio>
    <updated>0</updated>
    <his>None</his>
    <mat>30.0</mat>
    <kis>48.0</kis>
    <comp>None</comp>
    <phy>None</phy>
    <exam_id>3</exam_id>
    <bs>None</bs>
    <geo>74.0</geo>
    <form_pos>7</form_pos>
    <class_pos>0</class_pos>
    <points>0</points>
    <cre>None</cre>
    <totalled>0</totalled>
    <mean>0.0</mean>
  </exam_results>
  <exam_results>
    <hsc>None</hsc>
    <exam_result_id>11</exam_result_id>
    <chem>None</chem>
    <total>262.0</total>
    <eng>20.0</eng>
    <student_id>11</student_id>
    <msc>None</msc>
    <uploaded>0</uploaded>
    <bio>45.0</bio>
    <updated>0</updated>
    <his>None</his>
    <mat>30.0</mat>
    <kis>85.0</kis>
    <comp>None</comp>
    <phy>None</phy>
    <exam_id>3</exam_id>
    <bs>None</bs>
    <geo>82.0</geo>
    <form_pos>8</form_pos>
    <class_pos>2</class_pos>
    <points>0</points>
    <cre>None</cre>
    <totalled>0</totalled>
    <mean>0.0</mean>
  </exam_results>
  <exam_results>
    <hsc>None</hsc>
    <exam_result_id>12</exam_result_id>
    <chem>None</chem>
    <total>188.0</total>
    <eng>18.0</eng>
    <student_id>12</student_id>
    <msc>None</msc>
    <uploaded>0</uploaded>
    <bio>48.0</bio>
    <updated>0</updated>
    <his>None</his>
    <mat>36.0</mat>
    <kis>24.0</kis>
    <comp>None</comp>
    <phy>None</phy>
    <exam_id>3</exam_id>
    <bs>None</bs>
    <geo>62.0</geo>
    <form_pos>12</form_pos>
    <class_pos>9</class_pos>
    <points>0</points>
    <cre>None</cre>
    <totalled>0</totalled>
    <mean>0.0</mean>
  </exam_results>
  <exam_results>
    <hsc>None</hsc>
    <exam_result_id>13</exam_result_id>
    <chem>None</chem>
    <total>225.0</total>
    <eng>25.0</eng>
    <student_id>6</student_id>
    <msc>None</msc>
    <uploaded>0</uploaded>
    <bio>55.0</bio>
    <updated>0</updated>
    <his>None</his>
    <mat>35.0</mat>
    <kis>45.0</kis>
    <comp>None</comp>
    <phy>None</phy>
    <exam_id>2</exam_id>
    <bs>None</bs>
    <geo>65.0</geo>
    <form_pos>0</form_pos>
    <class_pos>0</class_pos>
    <points>0</points>
    <cre>None</cre>
    <totalled>0</totalled>
    <mean>0.0</mean>
  </exam_results>
  <exam_results>
    <hsc>None</hsc>
    <exam_result_id>14</exam_result_id>
    <chem>None</chem>
    <total>357.0</total>
    <eng>44.0</eng>
    <student_id>5</student_id>
    <msc>None</msc>
    <uploaded>0</uploaded>
    <bio>96.0</bio>
    <updated>0</updated>
    <his>None</his>
    <mat>84.0</mat>
    <kis>75.0</kis>
    <comp>None</comp>
    <phy>None</phy>
    <exam_id>2</exam_id>
    <bs>None</bs>
    <geo>58.0</geo>
    <form_pos>0</form_pos>
    <class_pos>0</class_pos>
    <points>0</points>
    <cre>None</cre>
    <totalled>0</totalled>
    <mean>0.0</mean>
  </exam_results>
  <exam_results>
    <hsc>None</hsc>
    <exam_result_id>15</exam_result_id>
    <chem>None</chem>
    <total>280.0</total>
    <eng>59.0</eng>
    <student_id>6</student_id>
    <msc>None</msc>
    <uploaded>0</uploaded>
    <bio>85.0</bio>
    <updated>0</updated>
    <his>None</his>
    <mat>35.0</mat>
    <kis>45.0</kis>
    <comp>None</comp>
    <phy>None</phy>
    <exam_id>5</exam_id>
    <bs>None</bs>
    <geo>56.0</geo>
    <form_pos>0</form_pos>
    <class_pos>0</class_pos>
    <points>0</points>
    <cre>None</cre>
    <totalled>0</totalled>
    <mean>0.0</mean>
  </exam_results>
  <exam_results>
    <hsc>None</hsc>
    <exam_result_id>16</exam_result_id>
    <chem>None</chem>
    <total>221.0</total>
    <eng>25.0</eng>
    <student_id>5</student_id>
    <msc>None</msc>
    <uploaded>0</uploaded>
    <bio>63.0</bio>
    <updated>0</updated>
    <his>None</his>
    <mat>48.0</mat>
    <kis>57.0</kis>
    <comp>None</comp>
    <phy>None</phy>
    <exam_id>3</exam_id>
    <bs>None</bs>
    <geo>28.0</geo>
    <form_pos>11</form_pos>
    <class_pos>8</class_pos>
    <points>0</points>
    <cre>None</cre>
    <totalled>0</totalled>
    <mean>0.0</mean>
  </exam_results>
  <exam_results>
    <hsc>None</hsc>
    <exam_result_id>17</exam_result_id>
    <chem>None</chem>
    <total>69.0</total>
    <eng>0.0</eng>
    <student_id>1</student_id>
    <msc>None</msc>
    <uploaded>0</uploaded>
    <bio>0.0</bio>
    <updated>0</updated>
    <his>None</his>
    <mat>0.0</mat>
    <kis>69.0</kis>
    <comp>None</comp>
    <phy>None</phy>
    <exam_id>5</exam_id>
    <bs>None</bs>
    <geo>None</geo>
    <form_pos>0</form_pos>
    <class_pos>0</class_pos>
    <points>35</points>
    <cre>None</cre>
    <totalled>0</totalled>
    <mean>0.0</mean>
  </exam_results>
  <exam_results>
    <hsc>None</hsc>
    <exam_result_id>18</exam_result_id>
    <chem>None</chem>
    <total>58.0</total>
    <eng>0.0</eng>
    <student_id>11</student_id>
    <msc>None</msc>
    <uploaded>0</uploaded>
    <bio>0.0</bio>
    <updated>0</updated>
    <his>None</his>
    <mat>0.0</mat>
    <kis>58.0</kis>
    <comp>None</comp>
    <phy>None</phy>
    <exam_id>5</exam_id>
    <bs>None</bs>
    <geo>None</geo>
    <form_pos>0</form_pos>
    <class_pos>0</class_pos>
    <points>0</points>
    <cre>None</cre>
    <totalled>0</totalled>
    <mean>0.0</mean>
  </exam_results>
  <exam_results>
    <hsc>None</hsc>
    <exam_result_id>19</exam_result_id>
    <chem>None</chem>
    <total>251.0</total>
    <eng>40.0</eng>
    <student_id>2</student_id>
    <msc>None</msc>
    <uploaded>0</uploaded>
    <bio>70.0</bio>
    <updated>0</updated>
    <his>None</his>
    <mat>62.0</mat>
    <kis>54.0</kis>
    <comp>None</comp>
    <phy>None</phy>
    <exam_id>1</exam_id>
    <bs>None</bs>
    <geo>25.0</geo>
    <form_pos>0</form_pos>
    <class_pos>0</class_pos>
    <points>0</points>
    <cre>None</cre>
    <totalled>0</totalled>
    <mean>0.0</mean>
  </exam_results>
  <exam_results>
    <hsc>None</hsc>
    <exam_result_id>20</exam_result_id>
    <chem>None</chem>
    <total>278.0</total>
    <eng>74.0</eng>
    <student_id>3</student_id>
    <msc>None</msc>
    <uploaded>0</uploaded>
    <bio>62.0</bio>
    <updated>0</updated>
    <his>None</his>
    <mat>48.0</mat>
    <kis>59.0</kis>
    <comp>None</comp>
    <phy>None</phy>
    <exam_id>1</exam_id>
    <bs>None</bs>
    <geo>35.0</geo>
    <form_pos>0</form_pos>
    <class_pos>0</class_pos>
    <points>0</points>
    <cre>None</cre>
    <totalled>0</totalled>
    <mean>0.0</mean>
  </exam_results>
  <exam_results>
    <hsc>None</hsc>
    <exam_result_id>21</exam_result_id>
    <chem>None</chem>
    <total>285.0</total>
    <eng>52.0</eng>
    <student_id>5</student_id>
    <msc>None</msc>
    <uploaded>0</uploaded>
    <bio>70.0</bio>
    <updated>0</updated>
    <his>None</his>
    <mat>59.0</mat>
    <kis>68.0</kis>
    <comp>None</comp>
    <phy>None</phy>
    <exam_id>1</exam_id>
    <bs>None</bs>
    <geo>36.0</geo>
    <form_pos>0</form_pos>
    <class_pos>0</class_pos>
    <points>0</points>
    <cre>None</cre>
    <totalled>0</totalled>
    <mean>0.0</mean>
  </exam_results>
  <exam_results>
    <hsc>None</hsc>
    <exam_result_id>22</exam_result_id>
    <chem>None</chem>
    <total>271.0</total>
    <eng>40.0</eng>
    <student_id>6</student_id>
    <msc>None</msc>
    <uploaded>0</uploaded>
    <bio>62.0</bio>
    <updated>0</updated>
    <his>None</his>
    <mat>62.0</mat>
    <kis>54.0</kis>
    <comp>None</comp>
    <phy>None</phy>
    <exam_id>1</exam_id>
    <bs>None</bs>
    <geo>53.0</geo>
    <form_pos>0</form_pos>
    <class_pos>0</class_pos>
    <points>0</points>
    <cre>None</cre>
    <totalled>0</totalled>
    <mean>0.0</mean>
  </exam_results>
  <exam_results>
    <hsc>None</hsc>
    <exam_result_id>23</exam_result_id>
    <chem>None</chem>
    <total>288.0</total>
    <eng>63.0</eng>
    <student_id>1</student_id>
    <msc>None</msc>
    <uploaded>0</uploaded>
    <bio>60.0</bio>
    <updated>0</updated>
    <his>None</his>
    <mat>59.0</mat>
    <kis>61.0</kis>
    <comp>None</comp>
    <phy>None</phy>
    <exam_id>1</exam_id>
    <bs>None</bs>
    <geo>45.0</geo>
    <form_pos>0</form_pos>
    <class_pos>0</class_pos>
    <points>50</points>
    <cre>None</cre>
    <totalled>0</totalled>
    <mean>0.0</mean>
  </exam_results>
  <exam_results>
    <hsc>None</hsc>
    <exam_result_id>24</exam_result_id>
    <chem>None</chem>
    <total>258.0</total>
    <eng>50.0</eng>
    <student_id>11</student_id>
    <msc>None</msc>
    <uploaded>0</uploaded>
    <bio>72.0</bio>
    <updated>0</updated>
    <his>None</his>
    <mat>51.0</mat>
    <kis>43.0</kis>
    <comp>None</comp>
    <phy>None</phy>
    <exam_id>1</exam_id>
    <bs>None</bs>
    <geo>42.0</geo>
    <form_pos>0</form_pos>
    <class_pos>0</class_pos>
    <points>0</points>
    <cre>None</cre>
    <totalled>0</totalled>
    <mean>0.0</mean>
  </exam_results>
</database>
